[
  {
    "company_name": "PentStark",
    "website": "https://pentstark.com",
    "career_page_url": "https://pentstark.com/careers/",
    "board_token": "https://pentstark.com/careers/",
    "domain_hint": "offensive security/AI security (India/EU remote)",
    "source_platforms": [
      "manual-target"
    ]
  },
  {
    "company_name": "ZynoSec",
    "website": "https://zynosec.com",
    "career_page_url": "https://zynosec.com/careers/",
    "board_token": "https://zynosec.com/careers/",
    "domain_hint": "pentest (India remote)",
    "source_platforms": [
      "manual-target"
    ]
  }
]